setup.py
odoo/addons/helpdesk_ticket_priority_filter/CHANGELOG.md
odoo/addons/helpdesk_ticket_priority_filter/README.rst
odoo/addons/helpdesk_ticket_priority_filter/__init__.py
odoo/addons/helpdesk_ticket_priority_filter/__manifest__.py
odoo/addons/helpdesk_ticket_priority_filter/i18n/ca_ES.po
odoo/addons/helpdesk_ticket_priority_filter/i18n/es.po
odoo/addons/helpdesk_ticket_priority_filter/models/__init__.py
odoo/addons/helpdesk_ticket_priority_filter/models/helpdesk_ticket.py
odoo/addons/helpdesk_ticket_priority_filter/models/helpdesk_ticket_team.py
odoo/addons/helpdesk_ticket_priority_filter/models/res_config_settings.py
odoo/addons/helpdesk_ticket_priority_filter/static/description/icon.png
odoo/addons/helpdesk_ticket_priority_filter/tests/__init__.py
odoo/addons/helpdesk_ticket_priority_filter/tests/test_helpdesk_ticket.py
odoo/addons/helpdesk_ticket_priority_filter/tests/test_helpdesk_ticket_team.py
odoo/addons/helpdesk_ticket_priority_filter/views/helpdesk_ticket_view.xml
odoo/addons/helpdesk_ticket_priority_filter/views/res_config_settings_view.xml
odoo_addon_helpdesk_ticket_priority_filter.egg-info/PKG-INFO
odoo_addon_helpdesk_ticket_priority_filter.egg-info/SOURCES.txt
odoo_addon_helpdesk_ticket_priority_filter.egg-info/dependency_links.txt
odoo_addon_helpdesk_ticket_priority_filter.egg-info/not-zip-safe
odoo_addon_helpdesk_ticket_priority_filter.egg-info/requires.txt
odoo_addon_helpdesk_ticket_priority_filter.egg-info/top_level.txt